src/__init__.py
src/hello_world.py
python_actions_pypi_test-1.0.0.dist-info/LICENSE
python_actions_pypi_test-1.0.0.dist-info/METADATA
python_actions_pypi_test-1.0.0.dist-info/WHEEL
python_actions_pypi_test-1.0.0.dist-info/top_level.txt
python_actions_pypi_test-1.0.0.dist-info/RECORD
