Metadata-Version: 2.1
Name: python-actions-pypi-test
Version: 1.0.0
Summary: Just a simple Hello World package
Home-page: https://github.com/vaisakhpisharody/python-actions-pypi-test
Author: Vaisakh Pisharody
Author-email: vaisakh.cob@gmail.com
License: UNKNOWN
Platform: UNKNOWN
Classifier: Programming Language :: Python :: 3
Classifier: License :: OSI Approved :: MIT License
